griffe_sphinx-0.2.0.dist-info/METADATA
griffe_sphinx-0.2.0.dist-info/WHEEL
griffe_sphinx-0.2.0.dist-info/entry_points.txt
griffe_sphinx-0.2.0.dist-info/licenses/LICENSE
griffe_sphinx/__init__.py
griffe_sphinx/_internal/__init__.py
griffe_sphinx/_internal/debug.py
griffe_sphinx/_internal/extension.py
griffe_sphinx/py.typed
griffe_sphinx-0.2.0.dist-info/RECORD
