Metadata-Version: 2.4
Name: griffe-sphinx
Version: 0.2.0
Summary: Parse Sphinx-comments above attributes as docstrings.
Author-Email: =?utf-8?q?Timoth=C3=A9e_Mazzucotelli?= <dev@pawamoy.fr>
License-Expression: ISC
License-File: LICENSE
Classifier: Development Status :: 4 - Beta
Classifier: Intended Audience :: Developers
Classifier: Programming Language :: Python
Classifier: Programming Language :: Python :: 3
Classifier: Programming Language :: Python :: 3 :: Only
Classifier: Programming Language :: Python :: 3.10
Classifier: Programming Language :: Python :: 3.11
Classifier: Programming Language :: Python :: 3.12
Classifier: Programming Language :: Python :: 3.13
Classifier: Programming Language :: Python :: 3.14
Classifier: Topic :: Documentation
Classifier: Topic :: Software Development
Classifier: Topic :: Utilities
Classifier: Typing :: Typed
Project-URL: Homepage, https://mkdocstrings.github.io/griffe-sphinx
Project-URL: Documentation, https://mkdocstrings.github.io/griffe-sphinx
Project-URL: Changelog, https://mkdocstrings.github.io/griffe-sphinx/changelog
Project-URL: Repository, https://github.com/mkdocstrings/griffe-sphinx
Project-URL: Issues, https://github.com/mkdocstrings/griffe-sphinx/issues
Project-URL: Discussions, https://github.com/mkdocstrings/griffe-sphinx/discussions
Project-URL: Gitter, https://gitter.im/mkdocstrings/griffe-sphinx
Project-URL: Funding, https://github.com/sponsors/pawamoy
Requires-Python: >=3.10
Requires-Dist: griffe>=0.49
